{
    "shapes": [
        {
            "coordinates": [
                {
                    "x": 50,
                    "y": 50,
                    "textX": 30,
                    "textY": 40,
                    "cubicCurveX1": 0,
                    "cubicCurveY1": 0,
                    "cubicCurveX2": 80,
                    "cubicCurveY2": 250
                },
                {
                    "x": 150,
                    "y": 250,
                    "textX": 130,
                    "textY": 260,
                    "cubicCurveX1": 250,
                    "cubicCurveY1": 250,
                    "cubicCurveX2": 250,
                    "cubicCurveY2": 250
                },
                {
                    "x": 250,
                    "y": 170,
                    "textX": 255,
                    "textY": 175,
                    "cubicCurveX1": 250,
                    "cubicCurveY1": 50,
                    "cubicCurveX2": 400,
                    "cubicCurveY2": 350
                },
                {
                    "x": 320,
                    "y": 280
                }
            ],
            "drawCoordinates": true,
            "drawWithCurve": true,
            "lineColor": "white",
            "fontColor": "#00FF00",
            "fillColor": "transparent"
        },
        {
            "coordinates": [
                {
                    "x": 50,
                    "y": 250,
                    "quadraticCurveX": 25,
                    "quadraticCurveY": 300
                },
                {
                    "x": 50,
                    "y": 350,
                    "quadraticCurveX": 100,
                    "quadraticCurveY": 375
                },
                {
                    "x": 150,
                    "y": 350
                }
            ],
            "lineColor": "yellow",
            "fillColor": "black",
            "drawWithCurve": true
        },
        {
            "coordinates": [
                {
                    "x": 250,
                    "y": 50,
                    "quadraticCurveX": 310,
                    "quadraticCurveY": 60
                },
                {
                    "x": 370,
                    "y": 50,
                    "quadraticCurveX": 400,
                    "quadraticCurveY": 75
                },
                {
                    "x": 370,
                    "y": 100
                }
            ],
            "lineColor": "yellow",
            "fillColor": "black",
            "drawWithCurve": true
        },
        {
            "coordinates": [
                {
                    "x": 270,
                    "y": 310,
                    "quadraticCurveX": 255,
                    "quadraticCurveY": 340
                },
                {
                    "x": 270,
                    "y": 360,
                    "quadraticCurveX": 255,
                    "quadraticCurveY": 340
                },
                {
                    "x": 230,
                    "y": 360
                }
            ],
            "lineColor": "yellow",
            "fillColor": "black",
            "drawWithCurve": true
        }
    ]
}